jaqpot_python_sdk/__about__.py
jaqpot_python_sdk/__init__.py
jaqpot_python_sdk/jaqpot_api_client.py
jaqpot_python_sdk/jaqpot_api_client_builder.py
jaqpot_python_sdk/jaqpot_api_http_client.py
jaqpot_python_sdk/types.py
jaqpot_python_sdk/exceptions/__init__.py
jaqpot_python_sdk/exceptions/exceptions.py
jaqpot_python_sdk/helpers/__init__.py
jaqpot_python_sdk/helpers/b64encoding.py
jaqpot_python_sdk/helpers/logging.py
jaqpot_python_sdk/helpers/url_utils.py
jaqpot_python_sdk/patches/patched_dataset.py
jaqpot_python_sdk-6.2.3.dist-info/METADATA
jaqpot_python_sdk-6.2.3.dist-info/WHEEL
jaqpot_python_sdk-6.2.3.dist-info/licenses/LICENSE.txt
jaqpot_python_sdk-6.2.3.dist-info/RECORD
